Workbook

Sheet Tableau
A1: Date | B1: Canal | C1: Impressions | D1: Clicks | E1: Dépenses (FCFA) | F1: Conversions | G1: Revenus (FCFA) | H1: CTR (taux de click par vue) | I1: CPA (cout par click) | J1: Taux de conversion | K1: CPA (cout par conversion) | L1: ROAS (rentabilité des depenses) | M1: efficacite
A2: 46054 | B2: Facebook Ads | C2: 12000 | D2: 360 | E2: 25000 | F2: 18 | G2: 180000 | H2: =Tableau1[[#This Row],[Clicks]]/Tableau1[[#This Row],[Impressions]] -> 0.03 | I2: =Tableau1[[#This Row],[Dépenses (FCFA)]]/Tableau1[[#This Row],[Clicks]] -> 69.444444 | J2: =Tableau1[[#This Row],[Conversions]]/Tableau1[[#This Row],[Clicks]] -> 0.05 | K2: =Tableau1[[#This Row],[Dépenses (FCFA)]]/Tableau1[[#This Row],[Conversions]] -> 1388.8889 | L2: =Tableau1[[#This Row],[Revenus (FCFA)]]/Tableau1[[#This Row],[Dépenses (FCFA)]] -> 7.2 | M2: =IF(Tableau1[[#This Row],[ROAS (rentabilité des depenses)]]>'Analyse '!$E$14,"PERFORMANT","SOUS PERFORMANT") -> SOUS PERFORMANT
A3: 46054 | B3: Google Ads | C3: 8000 | D3: 400 | E3: 30000 | F3: 25 | G3: 250000 | H3: =Tableau1[[#This Row],[Clicks]]/Tableau1[[#This Row],[Impressions]] -> 0.05 | I3: =Tableau1[[#This Row],[Dépenses (FCFA)]]/Tableau1[[#This Row],[Clicks]] -> 75 | J3: =Tableau1[[#This Row],[Conversions]]/Tableau1[[#This Row],[Clicks]] -> 0.0625 | K3: =Tableau1[[#This Row],[Dépenses (FCFA)]]/Tableau1[[#This Row],[Conversions]] -> 1200 | L3: =Tableau1[[#This Row],[Revenus (FCFA)]]/Tableau1[[#This Row],[Dépenses (FCFA)]] -> 8.3333333 | M3: =IF(Tableau1[[#This Row],[ROAS (rentabilité des depenses)]]>'Analyse '!$E$14,"PERFORMANT","SOUS PERFORMANT") -> PERFORMANT
A4: 46054 | B4: Instagram Ads | C4: 10000 | D4: 250 | E4: 20000 | F4: 15 | G4: 150000 | H4: =Tableau1[[#This Row],[Clicks]]/Tableau1[[#This Row],[Impressions]] -> 0.025 | I4: =Tableau1[[#This Row],[Dépenses (FCFA)]]/Tableau1[[#This Row],[Clicks]] -> 80 | J4: =Tableau1[[#This Row],[Conversions]]/Tableau1[[#This Row],[Clicks]] -> 0.06 | K4: =Tableau1[[#This Row],[Dépenses (FCFA)]]/Tableau1[[#This Row],[Conversions]] -> 1333.3333 | L4: =Tableau1[[#This Row],[Revenus (FCFA)]]/Tableau1[[#This Row],[Dépenses (FCFA)]] -> 7.5 | M4: =IF(Tableau1[[#This Row],[ROAS (rentabilité des depenses)]]>'Analyse '!$E$14,"PERFORMANT","SOUS PERFORMANT") -> SOUS PERFORMANT
A5: 46055 | B5: Facebook Ads | C5: 12200 | D5: 370 | E5: 25200 | F5: 19 | G5: 185000 | H5: =Tableau1[[#This Row],[Clicks]]/Tableau1[[#This Row],[Impressions]] -> 0.030327869 | I5: =Tableau1[[#This Row],[Dépenses (FCFA)]]/Tableau1[[#This Row],[Clicks]] -> 68.108108 | J5: =Tableau1[[#This Row],[Conversions]]/Tableau1[[#This Row],[Clicks]] -> 0.051351351 | K5: =Tableau1[[#This Row],[Dépenses (FCFA)]]/Tableau1[[#This Row],[Conversions]] -> 1326.3158 | L5: =Tableau1[[#This Row],[Revenus (FCFA)]]/Tableau1[[#This Row],[Dépenses (FCFA)]] -> 7.3412698 | M5: =IF(Tableau1[[#This Row],[ROAS (rentabilité des depenses)]]>'Analyse '!$E$14,"PERFORMANT","SOUS PERFORMANT") -> SOUS PERFORMANT
A6: 46055 | B6: Google Ads | C6: 8200 | D6: 410 | E6: 30500 | F6: 26 | G6: 255000 | H6: =Tableau1[[#This Row],[Clicks]]/Tableau1[[#This Row],[Impressions]] -> 0.05 | I6: =Tableau1[[#This Row],[Dépenses (FCFA)]]/Tableau1[[#This Row],[Clicks]] -> 74.390244 | J6: =Tableau1[[#This Row],[Conversions]]/Tableau1[[#This Row],[Clicks]] -> 0.063414634 | K6: =Tableau1[[#This Row],[Dépenses (FCFA)]]/Tableau1[[#This Row],[Conversions]] -> 1173.0769 | L6: =Tableau1[[#This Row],[Revenus (FCFA)]]/Tableau1[[#This Row],[Dépenses (FCFA)]] -> 8.3606557 | M6: =IF(Tableau1[[#This Row],[ROAS (rentabilité des depenses)]]>'Analyse '!$E$14,"PERFORMANT","SOUS PERFORMANT") -> PERFORMANT
A7: 46055 | B7: Instagram Ads | C7: 10200 | D7: 260 | E7: 20500 | F7: 16 | G7: 155000 | H7: =Tableau1[[#This Row],[Clicks]]/Tableau1[[#This Row],[Impressions]] -> 0.025490196 | I7: =Tableau1[[#This Row],[Dépenses (FCFA)]]/Tableau1[[#This Row],[Clicks]] -> 78.846154 | J7: =Tableau1[[#This Row],[Conversions]]/Tableau1[[#This Row],[Clicks]] -> 0.061538462 | K7: =Tableau1[[#This Row],[Dépenses (FCFA)]]/Tableau1[[#This Row],[Conversions]] -> 1281.25 | L7: =Tableau1[[#This Row],[Revenus (FCFA)]]/Tableau1[[#This Row],[Dépenses (FCFA)]] -> 7.5609756 | M7: =IF(Tableau1[[#This Row],[ROAS (rentabilité des depenses)]]>'Analyse '!$E$14,"PERFORMANT","SOUS PERFORMANT") -> SOUS PERFORMANT
A8: 46056 | B8: Facebook Ads | C8: 11800 | D8: 355 | E8: 24800 | F8: 17 | G8: 175000 | H8: =Tableau1[[#This Row],[Clicks]]/Tableau1[[#This Row],[Impressions]] -> 0.030084746 | I8: =Tableau1[[#This Row],[Dépenses (FCFA)]]/Tableau1[[#This Row],[Clicks]] -> 69.859155 | J8: =Tableau1[[#This Row],[Conversions]]/Tableau1[[#This Row],[Clicks]] -> 0.047887324 | K8: =Tableau1[[#This Row],[Dépenses (FCFA)]]/Tableau1[[#This Row],[Conversions]] -> 1458.8235 | L8: =Tableau1[[#This Row],[Revenus (FCFA)]]/Tableau1[[#This Row],[Dépenses (FCFA)]] -> 7.0564516 | M8: =IF(Tableau1[[#This Row],[ROAS (rentabilité des depenses)]]>'Analyse '!$E$14,"PERFORMANT","SOUS PERFORMANT") -> SOUS PERFORMANT
A9: 46056 | B9: Google Ads | C9: 8100 | D9: 395 | E9: 30200 | F9: 24 | G9: 248000 | H9: =Tableau1[[#This Row],[Clicks]]/Tableau1[[#This Row],[Impressions]] -> 0.048765432 | I9: =Tableau1[[#This Row],[Dépenses (FCFA)]]/Tableau1[[#This Row],[Clicks]] -> 76.455696 | J9: =Tableau1[[#This Row],[Conversions]]/Tableau1[[#This Row],[Clicks]] -> 0.060759494 | K9: =Tableau1[[#This Row],[Dépenses (FCFA)]]/Tableau1[[#This Row],[Conversions]] -> 1258.3333 | L9: =Tableau1[[#This Row],[Revenus (FCFA)]]/Tableau1[[#This Row],[Dépenses (FCFA)]] -> 8.2119205 | M9: =IF(Tableau1[[#This Row],[ROAS (rentabilité des depenses)]]>'Analyse '!$E$14,"PERFORMANT","SOUS PERFORMANT") -> PERFORMANT
A10: 46056 | B10: Instagram Ads | C10: 10100 | D10: 255 | E10: 20300 | F10: 15 | G10: 152000 | H10: =Tableau1[[#This Row],[Clicks]]/Tableau1[[#This Row],[Impressions]] -> 0.025247525 | I10: =Tableau1[[#This Row],[Dépenses (FCFA)]]/Tableau1[[#This Row],[Clicks]] -> 79.607843 | J10: =Tableau1[[#This Row],[Conversions]]/Tableau1[[#This Row],[Clicks]] -> 0.058823529 | K10: =Tableau1[[#This Row],[Dépenses (FCFA)]]/Tableau1[[#This Row],[Conversions]] -> 1353.3333 | L10: =Tableau1[[#This Row],[Revenus (FCFA)]]/Tableau1[[#This Row],[Dépenses (FCFA)]] -> 7.4876847 | M10: =IF(Tableau1[[#This Row],[ROAS (rentabilité des depenses)]]>'Analyse '!$E$14,"PERFORMANT","SOUS PERFORMANT") -> SOUS PERFORMANT
A11: 46057 | B11: Facebook Ads | C11: 12100 | D11: 365 | E11: 25100 | F11: 18 | G11: 182000 | H11: =Tableau1[[#This Row],[Clicks]]/Tableau1[[#This Row],[Impressions]] -> 0.030165289 | I11: =Tableau1[[#This Row],[Dépenses (FCFA)]]/Tableau1[[#This Row],[Clicks]] -> 68.767123 | J11: =Tableau1[[#This Row],[Conversions]]/Tableau1[[#This Row],[Clicks]] -> 0.049315068 | K11: =Tableau1[[#This Row],[Dépenses (FCFA)]]/Tableau1[[#This Row],[Conversions]] -> 1394.4444 | L11: =Tableau1[[#This Row],[Revenus (FCFA)]]/Tableau1[[#This Row],[Dépenses (FCFA)]] -> 7.250996 | M11: =IF(Tableau1[[#This Row],[ROAS (rentabilité des depenses)]]>'Analyse '!$E$14,"PERFORMANT","SOUS PERFORMANT") -> SOUS PERFORMANT
A12: 46057 | B12: Google Ads | C12: 8300 | D12: 415 | E12: 30800 | F12: 27 | G12: 260000 | H12: =Tableau1[[#This Row],[Clicks]]/Tableau1[[#This Row],[Impressions]] -> 0.05 | I12: =Tableau1[[#This Row],[Dépenses (FCFA)]]/Tableau1[[#This Row],[Clicks]] -> 74.216867 | J12: =Tableau1[[#This Row],[Conversions]]/Tableau1[[#This Row],[Clicks]] -> 0.065060241 | K12: =Tableau1[[#This Row],[Dépenses (FCFA)]]/Tableau1[[#This Row],[Conversions]] -> 1140.7407 | L12: =Tableau1[[#This Row],[Revenus (FCFA)]]/Tableau1[[#This Row],[Dépenses (FCFA)]] -> 8.4415584 | M12: =IF(Tableau1[[#This Row],[ROAS (rentabilité des depenses)]]>'Analyse '!$E$14,"PERFORMANT","SOUS PERFORMANT") -> PERFORMANT
A13: 46057 | B13: Instagram Ads | C13: 10300 | D13: 265 | E13: 20700 | F13: 16 | G13: 157000 | H13: =Tableau1[[#This Row],[Clicks]]/Tableau1[[#This Row],[Impressions]] -> 0.025728155 | I13: =Tableau1[[#This Row],[Dépenses (FCFA)]]/Tableau1[[#This Row],[Clicks]] -> 78.113208 | J13: =Tableau1[[#This Row],[Conversions]]/Tableau1[[#This Row],[Clicks]] -> 0.060377358 | K13: =Tableau1[[#This Row],[Dépenses (FCFA)]]/Tableau1[[#This Row],[Conversions]] -> 1293.75 | L13: =Tableau1[[#This Row],[Revenus (FCFA)]]/Tableau1[[#This Row],[Dépenses (FCFA)]] -> 7.5845411 | M13: =IF(Tableau1[[#This Row],[ROAS (rentabilité des depenses)]]>'Analyse '!$E$14,"PERFORMANT","SOUS PERFORMANT") -> SOUS PERFORMANT
... A91: 46083 | B91: Instagram Ads | C91: 11550 | D91: 327 | E91: 25000 | F91: 24 | G91: 204000 | H91: =Tableau1[[#This Row],[Clicks]]/Tableau1[[#This Row],[Impressions]] -> 0.028311688 | I91: =Tableau1[[#This Row],[Dépenses (FCFA)]]/Tableau1[[#This Row],[Clicks]] -> 76.452599 | J91: =Tableau1[[#This Row],[Conversions]]/Tableau1[[#This Row],[Clicks]] -> 0.073394495 | K91: =Tableau1[[#This Row],[Dépenses (FCFA)]]/Tableau1[[#This Row],[Conversions]] -> 1041.6667 | L91: =Tableau1[[#This Row],[Revenus (FCFA)]]/Tableau1[[#This Row],[Dépenses (FCFA)]] -> 8.16 | M91: =IF(Tableau1[[#This Row],[ROAS (rentabilité des depenses)]]>'Analyse '!$E$14,"PERFORMANT","SOUS PERFORMANT") -> PERFORMANT
K92: =AVERAGE(K2:K91) -> 1147.2791

Sheet TCD
A3: Somme de Dépenses (FCFA) | B3: Étiquettes de colonnes | H3: Somme de Dépenses (FCFA) | I3: Étiquettes de colonnes
A4: Étiquettes de lignes | B4: Facebook Ads | C4: Google Ads | D4: Instagram Ads | E4: Total général | H4: Étiquettes de lignes | I4: Facebook Ads | J4: Google Ads | K4: Instagram Ads | L4: Total général
A5: févr | B5: 750900 | C5: 928700 | D5: 620950 | E5: 2300550 | H5: févr | I5: 750900 | J5: 928700 | K5: 620950 | L5: 2300550
A6: mars | B6: 59400 | C6: 73800 | D6: 49800 | E6: 183000 | H6: mars | I6: 59400 | J6: 73800 | K6: 49800 | L6: 183000
A7: Total général | B7: 810300 | C7: 1002500 | D7: 670750 | E7: 2483550 | H7: Total général | I7: 810300 | J7: 1002500 | K7: 670750 | L7: 2483550
A11: Somme de Impressions | B11: Étiquettes de colonnes | I11: Étiquettes de colonnes
A12: Étiquettes de lignes | B12: Facebook Ads | C12: Google Ads | D12: Instagram Ads | E12: Total général | I12: Facebook Ads | K12: Google Ads | M12: Instagram Ads | O12: Total Somme de Conversions | P12: Total Somme de Impressions
A13: févr | B13: 361450 | C13: 245550 | D13: 301550 | E13: 908550 | H13: Étiquettes de lignes | I13: Somme de Conversions | J13: Somme de Impressions | K13: Somme de Conversions | L13: Somme de Impressions | M13: Somme de Conversions | N13: Somme de Impressions
A14: mars | B14: 28700 | C14: 19050 | D14: 23050 | E14: 70800 | H14: févr | I14: 622 | J14: 361450 | K14: 881 | L14: 245550 | M14: 531 | N14: 301550 | O14: 2034 | P14: 908550
A15: Total général | B15: 390150 | C15: 264600 | D15: 324600 | E15: 979350 | H15: mars | I15: 58 | J15: 28700 | K15: 78 | L15: 19050 | M15: 48 | N15: 23050 | O15: 184 | P15: 70800
H16: Total général | I16: 680 | J16: 390150 | K16: 959 | L16: 264600 | M16: 579 | N16: 324600 | O16: 2218 | P16: 979350
A18: Somme de CTR (taux de click par vue) | B18: Étiquettes de colonnes | H18: Somme de Revenus (FCFA) | I18: Étiquettes de colonnes
A19: Étiquettes de lignes | B19: Facebook Ads | C19: Google Ads | D19: Instagram Ads | E19: Total général | H19: Étiquettes de lignes | I19: Facebook Ads | J19: Google Ads | K19: Instagram Ads | L19: Total général
A20: févr | H20: févr | I20: 5562000 | J20: 7936000 | K20: 4909000 | L20: 18407000
A21: 01-févr | B21: 0.03 | C21: 0.05 | D21: 0.025 | E21: 0.105 | H21: mars | I21: 462000 | J21: 642000 | K21: 406000 | L21: 1510000
A22: 02-févr | B22: 0.030327869 | C22: 0.05 | D22: 0.025490196 | E22: 0.10581806 | H22: Total général | I22: 6024000 | J22: 8578000 | K22: 5315000 | L22: 19917000
A23: 03-févr | B23: 0.030084746 | C23: 0.048765432 | D23: 0.025247525 | E23: 0.1040977
A24: 04-févr | B24: 0.030165289 | C24: 0.05 | D24: 0.025728155 | E24: 0.10589344
A25: 05-févr | B25: 0.030292887 | C25: 0.049090909 | D25: 0.025560976 | E25: 0.10494477
A26: 06-févr | B26: 0.030539419 | C26: 0.05005988 | D26: 0.02589372 | E26: 0.10649302 | H26: Somme de CPA (cout par conversion) | I26: Étiquettes de colonnes
A27: 07-févr | B27: 0.030452675 | C27: 0.05 | D27: 0.025961538 | E27: 0.10641421 | H27: Étiquettes de lignes | I27: Facebook Ads | J27: Google Ads | K27: Instagram Ads | L27: Total général
A28: 08-févr | B28: 0.030491803 | C28: 0.050295858 | D28: 0.026028708 | E28: 0.10681637 | H28: févr | I28: 34278.789 | J28: 29798.613 | K28: 33162.134 | L28: 97239.535
A29: 09-févr | B29: 0.030487805 | C29: 0.050588235 | D29: 0.026190476 | E29: 0.10726652 | H29: mars | I29: 2048.2759 | J29: 1892.3077 | K29: 2075 | L29: 6015.5836
A30: 10-févr | B30: 0.030483871 | C30: 0.050877193 | D30: 0.026255924 | E30: 0.10761699 | H30: Total général | I30: 36327.065 | J30: 31690.92 | K30: 35237.134 | L30: 103255.12
A31: 11-févr | B31: 0.0304 | C31: 0.050930233 | D31: 0.026415094 | E31: 0.10774533
A32: 12-févr | B32: 0.030396825 | C32: 0.050867052 | D32: 0.026478873 | E32: 0.10774275
A33: 13-févr | B33: 0.030314961 | C33: 0.05091954 | D33: 0.026635514 | E33: 0.10787001
A34: 14-févr | B34: 0.0303125 | C34: 0.050857143 | D34: 0.026697674 | E34: 0.10786732
A35: 15-févr | B35: 0.030232558 | C35: 0.050909091 | D35: 0.026851852 | E35: 0.1079935 | H35: Somme de Conversions | I35: Étiquettes de colonnes
A36: 16-févr | B36: 0.030230769 | C36: 0.050847458 | D36: 0.026912442 | E36: 0.10799067 | H36: Étiquettes de lignes | I36: Facebook Ads | J36: Google Ads | K36: Instagram Ads | L36: Total général
A37: 17-févr | B37: 0.030152672 | C37: 0.050898876 | D37: 0.02706422 | E37: 0.10811577 | H37: mars | I37: 58 | J37: 78 | K37: 48 | L37: 184
A38: 18-févr | B38: 0.030151515 | C38: 0.050837989 | D38: 0.027123288 | E38: 0.10811279 | H38: Total général | I38: 58 | J38: 78 | K38: 48 | L38: 184
A39: 19-févr | B39: 0.030075188 | C39: 0.050888889 | D39: 0.027272727 | E39: 0.1082368
A40: 20-févr | B40: 0.030074627 | C40: 0.050828729 | D40: 0.027330317 | E40: 0.10823367
A41: 21-févr | B41: 0.03 | C41: 0.050879121 | D41: 0.027477477 | E41: 0.1083566
A42: 22-févr | B42: 0.03 | C42: 0.050819672 | D42: 0.027533632 | E42: 0.1083533
A43: 23-févr | B43: 0.029927007 | C43: 0.050869565 | D43: 0.027678571 | E43: 0.10847514 | H43: Somme de ROAS (rentabilité des depenses) | I43: Étiquettes de colonnes
A44: 24-févr | B44: 0.029927536 | C44: 0.050810811 | D44: 0.027733333 | E44: 0.10847168 | H44: Étiquettes de lignes | I44: Facebook Ads | J44: Google Ads | K44: Instagram Ads | L44: Total général
A45: 25-févr | B45: 0.029856115 | C45: 0.050860215 | D45: 0.027876106 | E45: 0.10859244 | H45: févr | I45: 207.1678 | J45: 239.09703 | K45: 221.00839 | L45: 667.27321
A46: 26-févr | B46: 0.029857143 | C46: 0.050802139 | D46: 0.027929515 | E46: 0.1085888 | H46: mars | I46: 15.555505 | J46: 17.398355 | K46: 16.305161 | L46: 49.259021
A47: 27-févr | B47: 0.029787234 | C47: 0.050851064 | D47: 0.028070175 | E47: 0.10870847 | H47: Total général | I47: 222.7233 | J47: 256.49539 | K47: 237.31355 | L47: 716.53224
A48: 28-févr | B48: 0.029788732 | C48: 0.050793651 | D48: 0.028122271 | E48: 0.10870465
A49: mars
A50: 01-mars | B50: 0.02972028 | C50: 0.050842105 | D50: 0.02826087 | E50: 0.10882325 | H50: Somme de CTR (taux de click par vue) | I50: Étiquettes de colonnes
A51: 02-mars | B51: 0.029722222 | C51: 0.05078534 | D51: 0.028311688 | E51: 0.10881925 | H51: Étiquettes de lignes | I51: Facebook Ads | J51: Google Ads | K51: Instagram Ads | L51: Total général
A52: Total général | B52: 0.90425425 | C52: 1.5167762 | D52: 0.80513286 | E52: 3.2261633 | H52: févr | I52: 0.84481175 | J52: 1.4151487 | K52: 0.7485603 | L52: 3.0085208
H53: mars | I53: 0.059442502 | J53: 0.10162745 | K53: 0.056572558 | L53: 0.21764251
H54: Total général | I54: 0.90425425 | J54: 1.5167762 | K54: 0.80513286 | L54: 3.2261633
A55: Étiquettes de lignes | B55: Somme de Dépenses (FCFA) | C55: Somme de Revenus (FCFA)
A56: <01/02/2026
A57: 01-févr | B57: 75000 | C57: 580000
A58: 02-févr | B58: 76200 | C58: 595000
A59: 03-févr | B59: 75300 | C59: 575000
A60: 04-févr | B60: 76600 | C60: 599000 | H60: Étiquettes de lignes | I60: Somme de ROAS (rentabilité des depenses) | K60: Somme de Taux de conversion | L60: Étiquettes de colonnes
A61: 05-févr | B61: 76150 | C61: 593000 | H61: 01-févr | K61: Étiquettes de lignes | L61: Facebook Ads | M61: Google Ads | N61: Instagram Ads | O61: (vide) | P61: Total général
A62: 06-févr | B62: 77000 | C62: 603000 | H62: Instagram Ads | I62: 7.5 | K62: <01/02/2026
A63: 07-févr | B63: 77400 | C63: 609000 | H63: 02-févr | K63: févr | L63: 1.5896765 | M63: 1.9787268 | N63: 1.8323411 | P63: 5.4007443
A64: 08-févr | B64: 77900 | C64: 615000 | H64: Instagram Ads | I64: 7.5609756 | K64: mars | L64: 0.1359923 | M64: 0.16115771 | N64: 0.14724065 | P64: 0.44439067
A65: 09-févr | B65: 78600 | C65: 622000 | H65: 03-févr | K65: Total général | L65: 1.7256688 | M65: 2.1398845 | N65: 1.9795817 | P65: 5.8451349
A66: 10-févr | B66: 79100 | C66: 627000 | H66: Instagram Ads | I66: 7.4876847
A67: 11-févr | B67: 79700 | C67: 635000 | H67: 04-févr
A68: 12-févr | B68: 80300 | C68: 641000 | H68: Instagram Ads | I68: 7.5845411
A69: 13-févr | B69: 81000 | C69: 647000 | H69: 05-févr
A70: 14-févr | B70: 81600 | C70: 652000 | H70: Instagram Ads | I70: 7.4757282
A71: 15-févr | B71: 82300 | C71: 659000 | H71: 06-févr
A72: 16-févr | B72: 82800 | C72: 666000 | H72: Instagram Ads | I72: 7.5779376
A73: 17-févr | B73: 83500 | C73: 672000 | H73: 07-févr
A74: 18-févr | B74: 84100 | C74: 677000 | H74: Instagram Ads | I74: 7.6555024
A75: 19-févr | B75: 84700 | C75: 684000 | H75: 08-févr
A76: 20-févr | B76: 85300 | C76: 689000 | H76: Instagram Ads | I76: 7.7142857
A77: 21-févr | B77: 86000 | C77: 697000 | H77: 09-févr
A78: 22-févr | B78: 86600 | C78: 703000 | H78: Instagram Ads | I78: 7.7830189
A79: 23-févr | B79: 87300 | C79: 711000 | H79: 10-févr
A80: 24-févr | B80: 87900 | C80: 717000 | H80: Instagram Ads | I80: 7.8403756
A81: 25-févr | B81: 88600 | C81: 725000 | H81: 11-févr
A82: 26-févr | B82: 89200 | C82: 731000 | H82: Instagram Ads | I82: 7.9069767
A83: 27-févr | B83: 89900 | C83: 739000 | H83: 12-févr
A84: 28-févr | B84: 90500 | C84: 744000 | H84: Instagram Ads | I84: 7.962963
A85: 01-mars | B85: 91200 | C85: 752000 | H85: 13-févr
A86: 02-mars | B86: 91800 | C86: 758000 | H86: Instagram Ads | I86: 7.9816514
A87: Total général | B87: 2483550 | C87: 19917000 | H87: 14-févr
H88: Instagram Ads | I88: 7.9545455
H89: 15-févr
H90: Instagram Ads | I90: 7.972973
H91: 16-févr
H92: Instagram Ads | I92: 8.0269058
H93: 17-févr
H94: Instagram Ads | I94: 8
H95: 18-févr
H96: Instagram Ads | I96: 8.0176211
H97: 19-févr
H98: Instagram Ads | I98: 8.0701754
H99: 20-févr
H100: Instagram Ads | I100: 8.0434783
H101: 21-févr
H102: Instagram Ads | I102: 8.0603448
H103: 22-févr
H104: Instagram Ads | I104: 8.0769231
H105: 23-févr
H106: Instagram Ads | I106: 8.0932203
...

Sheet Analyse 
D1: MOYENNE CPC TOTAL | E1: =AVERAGE(Tableau1[CPA (cout par click)]) -> 73.585388
D2: FACEBOOK ADS : | E2: =AVERAGE(Tableau!I2:I89) -> 73.522088
D3: GOOGLE ADS : | E3: =AVERAGE(Tableau!I3:I90) -> 73.599863
D4: INSTAGRAN ADS : | E4: =AVERAGE(Tableau!I4:I91) -> 73.61637
D7: CANAL | E7: SOMME IMPRESSIONS | F7: SOMME CLICKS | G7: SOMME CONVERSIONS | H7: DEPENSE | I7: CONVERSION | J7: REVENUES | K7: CTR REEL (taux de clicks) | L7: CPA REEL | M7: ROAS REEL
D8: FACEBOOK ADS | E8: =SUM(Tableau!C2:C89) -> 958250 | F8: =SUM(Tableau!D2:D89) -> 33050 | G8: =SUM(Tableau!F2:F89) -> 2155 | H8: =SUM(Tableau!E2:E89) -> 2421550 | I8: =SUM(Tableau!F2:F89) -> 2155 | J8: =SUM(Tableau!G2:G89) -> 19391000 | K8: =(F8/E8)*100 -> 3.4489956 | L8: =H8/G8 -> 1123.6891 | M8: ='Analyse '!J8/'Analyse '!H8 -> 8.007681
D9: GOOGLE ADS | E9: =SUM(Tableau!C3:C90) -> 955800 | F9: =SUM(Tableau!D3:D90) -> 33175 | G9: =SUM(Tableau!F3:F90) -> 2176 | H9: =SUM(Tableau!E15:E90) -> 2130500 | I9: =SUM(Tableau!F15:F90) -> 1940 | J9: =SUM(Tableau!G3:G90) -> 19533000 | K9: =(F9/E9)*100 -> 3.4709144 | L9: =H9/G9 -> 979.09007 | M9: ='Analyse '!J9/'Analyse '!H9 -> 9.1682704
D10: INSTAGRAM ADS | E10: =SUM(Tableau!C4:C91) -> 959350 | F10: =SUM(Tableau!D4:D91) -> 33102 | G10: =SUM(Tableau!F4:F91) -> 2175 | H10: =SUM(Tableau!E16:E91) -> 2124900 | I10: =SUM(Tableau!F13:F91) -> 1998 | J10: =SUM(Tableau!G4:G91) -> 19487000 | K10: =(F10/E10)*100 -> 3.4504612 | L10: =H10/G10 -> 976.96552 | M10: ='Analyse '!J10/'Analyse '!H10 -> 9.1707845
D11: TOTAL | E11: =SUM(E8:E10) -> 2873400 | F11: =SUM(F8:F10) -> 99327 | G11: =SUM(G8:G10) -> 6506 | H11: =SUM(H8:H10) -> 6676950 | I11: =SUM(I8:I10) -> 6093 | J11: =SUM(J8:J10) -> 58411000 | K11: =(F11/E11)*100 -> 3.4567759 | L11: =SUM(L8:L10) -> 3079.7447 | M11: =J11/H11 -> 8.748156
H12: =AVERAGE(H8:H10) -> 2225650
D14: ROAS GLOBAL | E14: =AVERAGE(Tableau!L2:L91) -> 7.9614693
D15: DEPENSE JOUR MOYENNE | E15: 27595
D16: CPA MOY | E16: 1147.2791

Sheet Graphique
B6: ROAS Global | C6: =GETPIVOTDATA("ROAS (rentabilité des depenses)",TCD!$H$43) -> 716.53224
B7: CPA Global | C7: =GETPIVOTDATA("CPA (cout par conversion)",TCD!$H$26) -> 103255.12
B8: CTR Global | C8: =GETPIVOTDATA("CTR (taux de click par vue)",TCD!$A$18) -> 3.2261633
B9: Total Conversions | C9: =GETPIVOTDATA("Conversions",TCD!$H$35) -> 184
B10: Total Revenus | C10: =GETPIVOTDATA("Revenus (FCFA)",TCD!$H$18) -> 19917000
J48: Étiquettes de lignes
J49: <01/02/2026
J50: 01-févr
J51: 02-févr
J52: 03-févr
J53: 04-févr
J54: 05-févr
J55: 06-févr
J56: 07-févr
J57: 08-févr
J58: 09-févr
J59: 10-févr
... J80: Total général
